ssdiff/__init__.py
ssdiff/clusters.py
ssdiff/core.py
ssdiff/io_utils.py
ssdiff/lexicon.py
ssdiff/preprocess.py
ssdiff/snippets.py
ssdiff/sweep.py
ssdiff/utils.py
ssdiff-0.1.9.dist-info/licenses/LICENSE
ssdiff-0.1.9.dist-info/METADATA
ssdiff-0.1.9.dist-info/WHEEL
ssdiff-0.1.9.dist-info/top_level.txt
ssdiff-0.1.9.dist-info/RECORD
