Metadata-Version: 2.4
Name: ssdiff
Version: 0.1.9
Summary: Supervised Semantic Differential (SSD): interpretable, embedding-based analysis of concept meaning in text.
Author-email: Hubert Plisiecki <hplisiecki@gmail.com>, Paweł Lenartowicz <pawellenartowicz@europe.com>
License-Expression: MIT
Project-URL: Homepage, https://github.com/hplisiecki/Supervised-Semantic-Differential
Project-URL: Repository, https://github.com/hplisiecki/Supervised-Semantic-Differential
Project-URL: Issues, https://github.com/hplisiecki/Supervised-Semantic-Differential/issues
Project-URL: Changelog, https://github.com/hplisiecki/Supervised-Semantic-Differential/releases
Keywords: NLP,semantics,word embeddings,psychometrics,semantic differential,computational social science
Classifier: Programming Language :: Python :: 3
Classifier: Programming Language :: Python :: 3 :: Only
Classifier: Programming Language :: Python :: 3.9
Classifier: Programming Language :: Python :: 3.10
Classifier: Programming Language :: Python :: 3.11
Classifier: Programming Language :: Python :: 3.12
Classifier: Operating System :: OS Independent
Classifier: Intended Audience :: Science/Research
Classifier: Topic :: Scientific/Engineering :: Information Analysis
Requires-Python: >=3.9
License-File: LICENSE
Requires-Dist: numpy>=1.26.4
Requires-Dist: pandas>=2.1.4
Requires-Dist: scikit-learn>=1.3.2
Requires-Dist: gensim>=4.3.2
Requires-Dist: spacy>=3.7.2
Requires-Dist: requests>=2.32.5
Requires-Dist: matplotlib>=3.10.7
Provides-Extra: dev
Requires-Dist: pytest>=7.0; extra == "dev"
Requires-Dist: pytest-cov>=4.0; extra == "dev"
Requires-Dist: ruff>=0.5; extra == "dev"
Requires-Dist: mypy>=1.6; extra == "dev"
Requires-Dist: build>=1.0.0; extra == "dev"
Requires-Dist: twine>=4.0; extra == "dev"
Provides-Extra: gui
Requires-Dist: PySide6>=6.6; extra == "gui"
Dynamic: license-file
